{
  "title": "Website Evidence Collection",
  "task_description": null,
  "uri_ins": "https://euskadi.eus",
  "uri_refs": [
    "https://euskadi.eus"
  ],
  "uri_dest": "https://www.euskadi.eus/hasiera/",
  "uri_redirects": [
    "https://euskadi.eus/",
    "https://www.euskadi.eus/"
  ],
  "secure_connection": {
    "https_support": true,
    "redirects": [
      "https://www.euskadi.eus/",
      "https://www.euskadi.eus/hasiera/"
    ],
    "https_redirect": true
  },
  "host": "euskadi.eus",
  "script": {
    "host": "sfod",
    "version": {
      "npm": "1.0.0",
      "commit": null
    },
    "cmd_args": "-q --overwrite https://euskadi.eus -- --ignore-certificate-errors",
    "environment": {
      "CHROME_DESKTOP": "code-url-handler.desktop"
    },
    "node_version": "v14.17.0"
  },
  "browser": {
    "name": "Chromium",
    "version": "HeadlessChrome/80.0.3987.0",
    "user_agent": "Mozilla/5.0 (X11; Linux x86_64) AppleWebKit/537.36 (KHTML, like Gecko) Chrome/72.0.3617.0 Safari/537.36",
    "platform": {
      "name": "Linux",
      "version": "5.8.0-53-generic"
    },
    "extra_headers": {},
    "preset_cookies": {}
  },
  "start_time": "2021-05-20T15:39:09.983Z",
  "end_time": "2021-05-20T15:39:17.190Z",
  "links": {
    "firstParty": [
      {
        "href": "http://euskadi.eus/ehaa",
        "inner_text": "EHAA",
        "inner_html": "<img alt=\"\" src=\"/images/web01-hasiera_bisitatuena-bopv-ehaa.gif\">EHAA"
      }
    ],
    "thirdParty": [
      {
        "href": "https://www.euskadi.eus/hasiera/",
        "inner_text": "Joan edukira",
        "inner_html": "Joan edukira"
      },
      {
        "href": "https://www.euskadi.eus/gaiak/",
        "inner_text": "Gaiak",
        "inner_html": "Gaiak"
      },
      {
        "href": "https://www.euskadi.eus/eusko-jaurlaritza/hasiera/",
        "inner_text": "Eusko Jaurlaritza",
        "inner_html": "Eusko Jaurlaritza"
      },
      {
        "href": "https://www.euskadi.eus/eusko-jaurlaritza/tramiteak-zerbitzuak/",
        "inner_text": "Tramiteak",
        "inner_html": "Tramiteak"
      },
      {
        "href": "https://www.euskadi.eus/eusko-jaurlaritza/zuzenean-herritarrentzako-zerbitzua/",
        "inner_text": "Kontaktua",
        "inner_html": "Kontaktua"
      },
      {
        "href": "https://www.euskadi.eus/bilaketa/",
        "inner_text": "Bilatzailea",
        "inner_html": "Bilatzailea"
      },
      {
        "href": "https://www.euskadi.eus/informazioa/-/euskadieus-web-mapa/",
        "inner_text": "Web-mapa",
        "inner_html": "Web-mapa"
      },
      {
        "href": "https://www.euskadi.eus/informazioa/-/erabilerraztasuna-euskadieus/",
        "inner_text": "Erabilerraztasuna",
        "inner_html": "Erabilerraztasuna"
      },
      {
        "href": "https://www.euskadi.eus/informazioa/-/lege-informazioa/",
        "inner_text": "Lege-informazioa",
        "inner_html": "Lege-informazioa"
      },
      {
        "href": "https://www.euskadi.eus/eusko-jaurlaritza/-/gobernu-irekia/",
        "inner_text": "Gobernu Irekia",
        "inner_html": "Gobernu Irekia"
      },
      {
        "href": "https://www.euskadi.eus/egoitza-elektronikoa/",
        "inner_text": "Egoitza Elektronikoa",
        "inner_html": "Egoitza Elektronikoa"
      },
      {
        "href": "https://www.euskadi.eus/inicio/",
        "inner_text": "ES",
        "inner_html": "<abbr xml:lang=\"es\" lang=\"es\" title=\"español\">es</abbr>"
      },
      {
        "href": "https://www.euskadi.eus/covid-19-koronabirus-berria/",
        "inner_text": "",
        "inner_html": "<img alt=\"COVID19, Eusko Jaurlaritzaren infomazioa eta neurriak\" src=\"/images/web01-hasiera-covid19-eu.jpg\">"
      },
      {
        "href": "https://www.euskadi.eus/nirekarpeta/",
        "inner_text": "Nire karpeta",
        "inner_html": "<img alt=\"\" src=\"/images/egoitza/web01-egoitza-mi_carpeta.gif\" width=\"85\" height=\"85\">Nire karpeta"
      },
      {
        "href": "http://www.osakidetza.euskadi.eus/r85-ghhome00/eu/",
        "inner_text": "Osakidetza",
        "inner_html": "<img alt=\"\" src=\"/images/web01-hasiera_bisitatuena_osakidetza.gif\">Osakidetza"
      },
      {
        "href": "https://www.euskalmet.euskadi.eus/hasiera/",
        "inner_text": "Euskalmet",
        "inner_html": "Euskalmet"
      },
      {
        "href": "https://www.euskadi.eus/enplegu-publikoa/",
        "inner_text": "Enplegu publikoa",
        "inner_html": "Enplegu publikoa"
      },
      {
        "href": "https://www.euskadi.eus/eusko-jaurlaritza/hezkuntza-saila/",
        "inner_text": "Hezkuntza",
        "inner_html": "Hezkuntza"
      },
      {
        "href": "http://www.euskadi.eus/eusko-jaurlaritza/tramiteak-zerbitzuak/?r01kQry=tT:ayuda_subvencion;cO:r01epd0122e4ed314423e0db04c97a47b5baa317f,r01epd0122e4edf39923e0db0b11fff216b637726;mA:documentLanguage.EQ.eu,procedureCollection.EQ.0,procedureStatus.EQ.16;pp:r01PageSize.20;p:Inter,Inter_portal&r01SearchEngine=meta",
        "inner_text": "Laguntzak eta diru-laguntzak",
        "inner_html": "Laguntzak eta diru-laguntzak"
      },
      {
        "href": "https://www.osanet.euskadi.net/o22War/O22ConexionServicioNuevaCitaServlet?servicio=16&idioma=eus",
        "inner_text": "Aurretiko hitzordua Osakidetzan",
        "inner_html": "Aurretiko hitzordua Osakidetzan"
      },
      {
        "href": "https://www.lanbide.euskadi.eus/lanbide-hasiera/",
        "inner_text": "Lanbide",
        "inner_html": "Lanbide"
      },
      {
        "href": "https://www.contratacion.euskadi.eus/informazio-orokorra-kontratatzailearen-profila/w32-kpeperfi/eu/",
        "inner_text": "Kontratatzailearen profila",
        "inner_html": "Kontratatzailearen profila"
      },
      {
        "href": "https://www.euskadi.eus/y22-payment/eu/p12iWar/p12iRPCDispatcherServlet?p12iIdioma=eu",
        "inner_text": "Nire ordainketa on-line",
        "inner_html": "Nire ordainketa on-line"
      },
      {
        "href": "https://www.euskadi.eus/elhuyar-hiztegia/",
        "inner_text": "Elhuyar Hiztegia",
        "inner_html": "Elhuyar Hiztegia"
      },
      {
        "href": "https://www.euskadi.eus/itzultzailea/",
        "inner_text": "Itzultzailea",
        "inner_html": "Itzultzailea"
      },
      {
        "href": "https://www.habe.euskadi.eus/hasiera/",
        "inner_text": "HABE",
        "inner_html": "HABE"
      },
      {
        "href": "https://www.euskadi.eus/gaiak/-/lana-eta-enplegua/",
        "inner_text": "Lana eta enplegua",
        "inner_html": "Lana eta enplegua"
      },
      {
        "href": "https://www.euskadi.eus/gaiak/-/ingurumena-eta-meteorologia/",
        "inner_text": "Ingurumena eta meteorologia",
        "inner_html": "Ingurumena eta meteorologia"
      },
      {
        "href": "https://www.euskadi.eus/gaiak/-/euskara/",
        "inner_text": "Euskara",
        "inner_html": "Euskara"
      },
      {
        "href": "https://www.euskadi.eus/gaiak/-/hezkuntza/",
        "inner_text": "Hezkuntza",
        "inner_html": "Hezkuntza"
      },
      {
        "href": "https://www.euskadi.eus/gaiak/-/osasuna/",
        "inner_text": "Osasuna",
        "inner_html": "Osasuna"
      },
      {
        "href": "https://www.euskadi.eus/gaiak/-/herri-administrazioa/",
        "inner_text": "Herri administrazioa",
        "inner_html": "Herri administrazioa"
      },
      {
        "href": "https://www.euskadi.eus/gaiak/-/turismoa-eta-aisia/",
        "inner_text": "Turismoa eta aisia",
        "inner_html": "Turismoa eta aisia"
      },
      {
        "href": "https://www.euskadi.eus/gaiak/-/etxebizitza/",
        "inner_text": "Etxebizitza",
        "inner_html": "Etxebizitza"
      },
      {
        "href": "https://www.euskadi.eus/gaiak/-/enpresa-eta-ekonomia-jarduerak/",
        "inner_text": "Enpresa eta ekonomia-jarduerak",
        "inner_html": "Enpresa eta ekonomia-jarduerak"
      },
      {
        "href": "https://www.euskadi.eus/gaiak/-/kultura-eta-kirola/",
        "inner_text": "Kultura eta kirola",
        "inner_html": "Kultura eta kirola"
      },
      {
        "href": "https://www.euskadi.eus/gaiak/-/familia-bikotea-eta-gizarte-gaiak/",
        "inner_text": "Familia, bikotea eta gizarte-gaiak",
        "inner_html": "Familia, bikotea eta gizarte-gaiak"
      },
      {
        "href": "https://www.euskadi.eus/gaiak/-/trafikoa-garraioak-eta-segurtasuna/",
        "inner_text": "Trafikoa, garraioak eta segurtasuna",
        "inner_html": "Trafikoa, garraioak eta segurtasuna"
      },
      {
        "href": "https://www.euskadi.eus/gaiak/-/lurraldea-eta-geografia/",
        "inner_text": "Lurraldea eta geografia",
        "inner_html": "Lurraldea eta geografia"
      },
      {
        "href": "https://www.euskadi.eus/eusko-jaurlaritza/lehendakaritza/",
        "inner_text": "Lehendakaritza",
        "inner_html": "Lehendakaritza"
      },
      {
        "href": "https://www.euskadi.eus/eusko-jaurlaritza/segurtasun-saila/",
        "inner_text": "Segurtasuna",
        "inner_html": "Segurtasuna"
      },
      {
        "href": "https://www.euskadi.eus/eusko-jaurlaritza/lan-enplegu-saila/",
        "inner_text": "Lana eta Enplegua",
        "inner_html": "Lana eta Enplegua"
      },
      {
        "href": "https://www.euskadi.eus/eusko-jaurlaritza/gobernantza-publiko-autogobernu-saila/",
        "inner_text": "Gobernantza Publikoa eta Autogobernua",
        "inner_html": "Gobernantza Publikoa eta Autogobernua"
      },
      {
        "href": "https://www.euskadi.eus/eusko-jaurlaritza/ekonomiaren-garapen-jasangarritasun-ingurumen-saila/",
        "inner_text": "Ekonomiaren Garapena, Jasangarritasuna eta Ingurumena",
        "inner_html": "Ekonomiaren Garapena, Jasangarritasuna eta Ingurumena"
      },
      {
        "href": "https://www.euskadi.eus/eusko-jaurlaritza/ekonomia-ogasun-saila/",
        "inner_text": "Ekonomia eta Ogasuna",
        "inner_html": "Ekonomia eta Ogasuna"
      },
      {
        "href": "https://www.euskadi.eus/eusko-jaurlaritza/lurralde-plangintza-etxebizitza-garraio-saila/",
        "inner_text": "Lurralde Plangintza, Etxebizitza eta Garraioak",
        "inner_html": "Lurralde Plangintza, Etxebizitza eta Garraioak"
      },
      {
        "href": "https://www.euskadi.eus/eusko-jaurlaritza/osasun-saila",
        "inner_text": "Osasuna",
        "inner_html": "Osasuna"
      },
      {
        "href": "https://www.euskadi.eus/eusko-jaurlaritza/berdintasuna-justizia-gizarte-politiketako-saila/",
        "inner_text": "Berdintasuna, Justizia eta Gizarte Politikak",
        "inner_html": "Berdintasuna, Justizia eta Gizarte Politikak"
      },
      {
        "href": "https://www.euskadi.eus/eusko-jaurlaritza/kultura-hizkuntza-politika-saila/",
        "inner_text": "Kultura eta Hizkuntza Politika",
        "inner_html": "Kultura eta Hizkuntza Politika"
      },
      {
        "href": "https://www.euskadi.eus/eusko-jaurlaritza/turismo-merkataritza-kontsumo-saila/",
        "inner_text": "Turismoa, Merkataritza eta Kontsumoa",
        "inner_html": "Turismoa, Merkataritza eta Kontsumoa"
      },
      {
        "href": "https://www.emakunde.euskadi.eus/",
        "inner_text": "Emakunde",
        "inner_html": "Emakunde"
      },
      {
        "href": "https://eu.eustat.eus/",
        "inner_text": "EUSTAT",
        "inner_html": "EUSTAT"
      },
      {
        "href": "https://www.gogora.euskadi.eus/",
        "inner_text": "Gogora Institutoa",
        "inner_html": "Gogora Institutoa"
      },
      {
        "href": "https://www.habe.euskadi.eus/",
        "inner_text": "HABE",
        "inner_html": "HABE"
      },
      {
        "href": "https://www.ivap.euskadi.eus/",
        "inner_text": "IVAP",
        "inner_html": "IVAP"
      },
      {
        "href": "https://www.kontsumobide.euskadi.eus/",
        "inner_text": "Kontsumobide",
        "inner_html": "Kontsumobide"
      },
      {
        "href": "https://www.lanbide.euskadi.eus/",
        "inner_text": "Lanbide",
        "inner_html": "Lanbide"
      },
      {
        "href": "https://www.osakidetza.euskadi.eus/",
        "inner_text": "Osakidetza",
        "inner_html": "Osakidetza"
      },
      {
        "href": "https://www.osalan.euskadi.eus/",
        "inner_text": "Osalan",
        "inner_html": "Osalan"
      },
      {
        "href": "https://www.arkauteakademia.net/",
        "inner_text": "Polizia eta Larrialdietako Akademia",
        "inner_html": "Polizia eta Larrialdietako Akademia"
      },
      {
        "href": "https://www2.irekia.euskadi.eus/eu",
        "inner_text": "...erakunde guztiak",
        "inner_html": "...erakunde guztiak"
      },
      {
        "href": "https://www.alava.net/",
        "inner_text": "Arabako Foru Aldundia",
        "inner_html": "Arabako Foru Aldundia"
      },
      {
        "href": "https://www.bizkaia.eus/",
        "inner_text": "Bizkaiko Foru Aldundia",
        "inner_html": "Bizkaiko Foru Aldundia"
      },
      {
        "href": "https://www.gipuzkoa.eus/",
        "inner_text": "Gipuzkoako Foru Aldundia",
        "inner_html": "Gipuzkoako Foru Aldundia"
      },
      {
        "href": "https://bilbao.eus/",
        "inner_text": "Bilboko Udala",
        "inner_html": "Bilboko Udala"
      },
      {
        "href": "https://www.donostia.eus/",
        "inner_text": "Donostiako Udala",
        "inner_html": "Donostiako Udala"
      },
      {
        "href": "https://www.vitoria-gasteiz.org/",
        "inner_text": "Vitoria-Gasteizko Udala",
        "inner_html": "Vitoria-Gasteizko Udala"
      },
      {
        "href": "https://www.eudel.eus/eu",
        "inner_text": "EUDEL",
        "inner_html": "EUDEL"
      },
      {
        "href": "https://www.irekia.euskadi.eus/eu",
        "inner_text": "Irekia, herritarren parte-hartzeko bideak",
        "inner_html": "<img alt=\"\" src=\"/images/web01-hasiera-irekia.gif\">Irekia, herritarren parte-hartzeko bideak"
      },
      {
        "href": "https://www.euskadi.eus/eusko-jaurlaritza/-/ezagutu-eusko-jaurlaritza/",
        "inner_text": "Ezagutu Jaurlaritza",
        "inner_html": "Ezagutu Jaurlaritza"
      },
      {
        "href": "https://www.euskadi.eus/eusko-jaurlaritza/-/eusko-jaurlaritzaren-sailak-eta-erakundeak/",
        "inner_text": "Sailak eta erakundeak",
        "inner_html": "Sailak eta erakundeak"
      },
      {
        "href": "https://www.euskadi.eus/eusko-jaurlaritza/tramiteak-zerbitzuak/?r01kQry=tT:ayuda_subvencion;cO:r01epd0122e4ed314423e0db04c97a47b5baa317f,r01epd0122e4edf39923e0db0b11fff216b637726;mA:documentLanguage.EQ.eu,procedureCollection.EQ.0,procedureStatus.EQ.16;pp:r01PageSize.20;p:Inter,Inter_portal&r01SearchEngine=meta",
        "inner_text": "Diru-laguntzak",
        "inner_html": "Diru-laguntzak"
      },
      {
        "href": "https://www.contratacion.euskadi.eus/w32-home/eu/",
        "inner_text": "Kontratazioak",
        "inner_html": "Kontratazioak"
      },
      {
        "href": "https://www.euskadi.eus/nireordainketa/",
        "inner_text": "Nire ordainketa",
        "inner_html": "Nire ordainketa"
      },
      {
        "href": "https://www.trafikoa.eus/",
        "inner_text": "Trafikoaren egoera",
        "inner_html": "Trafikoaren egoera"
      },
      {
        "href": "https://www.euskadi.eus/eusko-jaurlaritza/estatistika/",
        "inner_text": "Estatistika",
        "inner_html": "Estatistika"
      },
      {
        "href": "https://www.euskadi.eus/ehaa",
        "inner_text": "Euskal Herriko Agintaritzaren Aldizkaria",
        "inner_html": "Euskal Herriko&nbsp;Agintaritzaren Aldizkaria"
      },
      {
        "href": "http://www.araba.eus/botha",
        "inner_text": "Arabako Aldizkari Ofiziala",
        "inner_html": "Arabako Aldizkari Ofiziala"
      },
      {
        "href": "http://apps.bizkaia.eus/BT00/BAO_BOB?idi=eu",
        "inner_text": "Bizkaiko Aldizkari Ofiziala",
        "inner_html": "Bizkaiko Aldizkari Ofiziala"
      },
      {
        "href": "https://egoitza.gipuzkoa.eus/eu/GAO",
        "inner_text": "Gipuzkoako Aldizkari Ofiziala",
        "inner_html": "Gipuzkoako Aldizkari Ofiziala"
      },
      {
        "href": "http://www.boe.es/index.php?lang=eu",
        "inner_text": "Estatuko Aldizkari Ofiziala",
        "inner_html": "Estatuko Aldizkari Ofiziala"
      },
      {
        "href": "http://eur-lex.europa.eu/oj/direct-access.html?locale=es",
        "inner_text": "Europar Batasuneko Aldizkari Ofiziala",
        "inner_html": "Europar Batasuneko Aldizkari Ofiziala"
      },
      {
        "href": "https://www.euskadi.eus/eusko-jaurlaritza/web-zerbitzua/hasiera/",
        "inner_text": "Eusko Jaurlaritzaren Web Zerbitzuak",
        "inner_html": "Eusko Jaurlaritzaren Web Zerbitzuak"
      }
    ],
    "social": [],
    "keywords": []
  },
  "unsafeForms": [],
  "browsing_history": [
    "https://www.euskadi.eus/hasiera/"
  ],
  "websockets": {},
  "cookies": [
    {
      "name": "r01euskadiCookie",
      "value": "web01_eu",
      "domain": "euskadi.eus",
      "path": "/",
      "expires": 2088085150.566941,
      "size": 24,
      "httpOnly": false,
      "secure": false,
      "session": false,
      "expiresUTC": "2036-03-02T15:39:10.566Z",
      "expiresDays": 5400,
      "log": {
        "stack": [
          {
            "fileName": "https://www.euskadi.eus/hasiera/",
            "source": "set in Set-Cookie HTTP response header for https://www.euskadi.eus/hasiera/"
          }
        ],
        "type": "Cookie.HTTP",
        "timestamp": "2021-05-20T15:39:10.572Z",
        "location": "about:blank"
      },
      "firstPartyStorage": true
    },
    {
      "name": "r01euskadiUserCookie",
      "value": "YKaCnrEsZDLYjuUusejk6wAAAkA",
      "domain": "euskadi.eus",
      "path": "/",
      "expires": 2088085150.566787,
      "size": 47,
      "httpOnly": false,
      "secure": false,
      "session": false,
      "expiresUTC": "2036-03-02T15:39:10.566Z",
      "expiresDays": 5400,
      "log": {
        "stack": [
          {
            "fileName": "https://www.euskadi.eus/hasiera/",
            "source": "set in Set-Cookie HTTP response header for https://www.euskadi.eus/hasiera/"
          }
        ],
        "type": "Cookie.HTTP",
        "timestamp": "2021-05-20T15:39:10.572Z",
        "location": "about:blank"
      },
      "firstPartyStorage": true
    },
    {
      "name": "_ga",
      "value": "GA1.2.1638636105.1621525151",
      "domain": "euskadi.eus",
      "path": "/",
      "expires": 1684597151,
      "size": 30,
      "httpOnly": false,
      "secure": false,
      "session": false,
      "expiresUTC": "2023-05-20T15:39:11.000Z",
      "expiresDays": 730,
      "log": {
        "stack": [
          {
            "columnNumber": 495,
            "lineNumber": 30,
            "fileName": "https://www.google-analytics.com/analytics.js",
            "functionName": "zc",
            "source": "    at zc (https://www.google-analytics.com/analytics.js:30:495)"
          },
          {
            "columnNumber": 15,
            "lineNumber": 60,
            "fileName": "https://www.google-analytics.com/analytics.js",
            "functionName": "ma",
            "source": "    at ma (https://www.google-analytics.com/analytics.js:60:15)"
          }
        ],
        "type": "Cookie.JS",
        "timestamp": "2021-05-20T15:39:11.450Z",
        "location": "https://www.euskadi.eus/hasiera/"
      },
      "firstPartyStorage": true
    },
    {
      "name": "_gid",
      "value": "GA1.2.81269268.1621525151",
      "domain": "euskadi.eus",
      "path": "/",
      "expires": 1621611551,
      "size": 29,
      "httpOnly": false,
      "secure": false,
      "session": false,
      "expiresUTC": "2021-05-21T15:39:11.000Z",
      "expiresDays": 1,
      "log": {
        "stack": [
          {
            "columnNumber": 495,
            "lineNumber": 30,
            "fileName": "https://www.google-analytics.com/analytics.js",
            "functionName": "zc",
            "source": "    at zc (https://www.google-analytics.com/analytics.js:30:495)"
          },
          {
            "columnNumber": 401,
            "lineNumber": 59,
            "fileName": "https://www.google-analytics.com/analytics.js",
            "functionName": "ma",
            "source": "    at ma (https://www.google-analytics.com/analytics.js:59:401)"
          }
        ],
        "type": "Cookie.JS",
        "timestamp": "2021-05-20T15:39:11.451Z",
        "location": "https://www.euskadi.eus/hasiera/"
      },
      "firstPartyStorage": true
    },
    {
      "name": "_gat",
      "value": "1",
      "domain": "euskadi.eus",
      "path": "/",
      "expires": 1621525211,
      "size": 5,
      "httpOnly": false,
      "secure": false,
      "session": false,
      "expiresUTC": "2021-05-20T15:40:11.000Z",
      "expiresDays": 0,
      "log": {
        "stack": [
          {
            "columnNumber": 495,
            "lineNumber": 30,
            "fileName": "https://www.google-analytics.com/analytics.js",
            "functionName": "zc",
            "source": "    at zc (https://www.google-analytics.com/analytics.js:30:495)"
          },
          {
            "columnNumber": 31,
            "lineNumber": 73,
            "fileName": "https://www.google-analytics.com/analytics.js",
            "functionName": "Qd",
            "source": "    at Qd (https://www.google-analytics.com/analytics.js:73:31)"
          }
        ],
        "type": "Cookie.JS",
        "timestamp": "2021-05-20T15:39:11.515Z",
        "location": "https://www.euskadi.eus/hasiera/"
      },
      "firstPartyStorage": true
    },
    {
      "name": "_gat_globalEus",
      "value": "1",
      "domain": "euskadi.eus",
      "path": "/",
      "expires": 1621525211,
      "size": 15,
      "httpOnly": false,
      "secure": false,
      "session": false,
      "expiresUTC": "2021-05-20T15:40:11.000Z",
      "expiresDays": 0,
      "log": {
        "stack": [
          {
            "columnNumber": 495,
            "lineNumber": 30,
            "fileName": "https://www.google-analytics.com/analytics.js",
            "functionName": "zc",
            "source": "    at zc (https://www.google-analytics.com/analytics.js:30:495)"
          },
          {
            "columnNumber": 31,
            "lineNumber": 73,
            "fileName": "https://www.google-analytics.com/analytics.js",
            "functionName": "Qd",
            "source": "    at Qd (https://www.google-analytics.com/analytics.js:73:31)"
          }
        ],
        "type": "Cookie.JS",
        "timestamp": "2021-05-20T15:39:11.521Z",
        "location": "https://www.euskadi.eus/hasiera/"
      },
      "firstPartyStorage": true
    },
    {
      "name": "r01PortalInfo",
      "value": "web01-hasiera/eu",
      "domain": "www.euskadi.eus",
      "path": "/",
      "expires": -1,
      "size": 29,
      "httpOnly": false,
      "secure": false,
      "session": true,
      "log": {
        "stack": [
          {
            "fileName": "https://www.euskadi.eus/hasiera/",
            "source": "set in Set-Cookie HTTP response header for https://www.euskadi.eus/hasiera/"
          }
        ],
        "type": "Cookie.HTTP",
        "timestamp": "2021-05-20T15:39:10.572Z",
        "location": "about:blank"
      },
      "firstPartyStorage": false
    }
  ],
  "localStorage": {},
  "beacons": [
    {
      "url": "https://www.google-analytics.com/j/collect?v=1&_v=j90&aip=1&a=189306332&t=pageview&_s=1&dl=https%3A%2F%2Fwww.euskadi.eus%2Fhasiera%2F&ul=en-us&de=windows-1252&dt=Euskadi.eus%20-%20Eusko%20Jaurlaritzaren%20informazioa%2C%20tramiteak%20eta%20zerbitzuak&sd=24-bit&sr=1680x927&vp=1680x927&je=0&_u=aEDAAEABAAAAAC~&jid=383053085&gjid=390643498&cid=1638636105.1621525151&tid=UA-9512435-41&_gid=81269268.1621525151&_r=1&_slc=1&cd1=web01&cg3=web01&z=1681380258",
      "query": {
        "v": 1,
        "_v": "j90",
        "aip": 1,
        "a": 189306332,
        "t": "pageview",
        "_s": 1,
        "dl": "https://www.euskadi.eus/hasiera/",
        "ul": "en-us",
        "de": "windows-1252",
        "dt": "Euskadi.eus - Eusko Jaurlaritzaren informazioa, tramiteak eta zerbitzuak",
        "sd": "24-bit",
        "sr": "1680x927",
        "vp": "1680x927",
        "je": 0,
        "_u": "aEDAAEABAAAAAC~",
        "jid": 383053085,
        "gjid": 390643498,
        "cid": 1638636105.1621525,
        "tid": "UA-9512435-41",
        "_gid": 81269268.16215251,
        "_r": 1,
        "_slc": 1,
        "cd1": "web01",
        "cg3": "web01",
        "z": 1681380258
      },
      "filter": "/collect?*&cid=",
      "listName": "easyprivacy.txt",
      "log": {
        "stack": [
          {
            "fileName": "https://www.euskadi.eus/hasiera/",
            "source": "requested from https://www.euskadi.eus/hasiera/ and matched with easyprivacy.txt filter /collect?*&cid="
          }
        ],
        "timestamp": "2021-05-20T15:39:11.522Z"
      },
      "occurrances": 2
    },
    {
      "url": "https://www.google-analytics.com/analytics.js",
      "query": null,
      "filter": "||google-analytics.com/analytics.js",
      "listName": "easyprivacy.txt",
      "log": {
        "stack": [
          {
            "fileName": "https://www.euskadi.eus/hasiera/",
            "source": "requested from https://www.euskadi.eus/hasiera/ and matched with easyprivacy.txt filter ||google-analytics.com/analytics.js"
          }
        ],
        "timestamp": "2021-05-20T15:39:11.200Z"
      },
      "occurrances": 1
    }
  ],
  "hosts": {
    "requests": {
      "firstParty": [
        "euskadi.eus"
      ],
      "thirdParty": [
        "www.euskadi.eus",
        "fonts.googleapis.com",
        "fonts.gstatic.com",
        "www.google-analytics.com"
      ]
    },
    "beacons": {
      "firstParty": [],
      "thirdParty": [
        "www.google-analytics.com"
      ]
    },
    "cookies": {
      "firstParty": [
        "euskadi.eus"
      ],
      "thirdParty": [
        "www.euskadi.eus"
      ]
    },
    "localStorage": {
      "firstParty": [],
      "thirdParty": []
    },
    "links": {
      "firstParty": [
        "euskadi.eus"
      ],
      "thirdParty": [
        "www.euskadi.eus",
        "www.osakidetza.euskadi.eus",
        "www.euskalmet.euskadi.eus",
        "www.osanet.euskadi.net",
        "www.lanbide.euskadi.eus",
        "www.contratacion.euskadi.eus",
        "www.habe.euskadi.eus",
        "www.emakunde.euskadi.eus",
        "eu.eustat.eus",
        "www.gogora.euskadi.eus",
        "www.ivap.euskadi.eus",
        "www.kontsumobide.euskadi.eus",
        "www.osalan.euskadi.eus",
        "www.arkauteakademia.net",
        "www2.irekia.euskadi.eus",
        "www.alava.net",
        "www.bizkaia.eus",
        "www.gipuzkoa.eus",
        "bilbao.eus",
        "www.donostia.eus",
        "www.vitoria-gasteiz.org",
        "www.eudel.eus",
        "www.irekia.euskadi.eus",
        "www.trafikoa.eus",
        "www.araba.eus",
        "apps.bizkaia.eus",
        "egoitza.gipuzkoa.eus",
        "www.boe.es",
        "eur-lex.europa.eu"
      ]
    }
  }
}